vrt_python/__init__.py
vrt_python/cli.py
vrt_python-0.2.0.dist-info/LICENSE
vrt_python-0.2.0.dist-info/METADATA
vrt_python-0.2.0.dist-info/WHEEL
vrt_python-0.2.0.dist-info/entry_points.txt
vrt_python-0.2.0.dist-info/top_level.txt
vrt_python-0.2.0.dist-info/RECORD
