Metadata-Version: 2.1
Name: vrt_python
Version: 0.2.0
Summary: A CLI tool for visual regression testing
Home-page: https://github.com/vshkodin/vrt-python
Author: Vladimir Shkodin
Author-email: v.s.shkodin@gmail.com
Classifier: Programming Language :: Python :: 3
Classifier: License :: OSI Approved :: MIT License
Classifier: Operating System :: OS Independent
Requires-Python: >=3.9
License-File: LICENSE
Requires-Dist: Pillow ==10.3.0
Requires-Dist: numpy ==1.26.4
